{
	"animations": [
		{
			"offsets": [
				0,
				0
			],
			"loop": false,
			"fps": 24,
			"anim": "idle",
			"indices": [],
			"name": "idle"
		},
		{
			"offsets": [
				0,
				0
			],
			"loop": false,
			"fps": 24,
			"anim": "singLEFT",
			"indices": [],
			"name": "singleft"
		},
		{
			"offsets": [
				0,
				0
			],
			"loop": false,
			"fps": 24,
			"anim": "singDOWN",
			"indices": [],
			"name": "singdown"
		},
		{
			"offsets": [
				0,
				0
			],
			"loop": false,
			"fps": 24,
			"anim": "singUP",
			"indices": [],
			"name": "singup"
		},
		{
			"offsets": [
				0,
				0
			],
			"loop": false,
			"fps": 24,
			"anim": "singRIGHT",
			"indices": [],
			"name": "singright"
		},
		{
			"loop": false,
			"offsets": [
				0,
				0
			],
			"anim": "singLEFTmiss",
			"fps": 1,
			"name": "missleft",
			"indices": []
		},
		{
			"loop": false,
			"offsets": [
				0,
				0
			],
			"anim": "singDOWNmiss",
			"fps": 1,
			"name": "missdown",
			"indices": []
		},
		{
			"loop": false,
			"offsets": [
				0,
				0
			],
			"anim": "singUPmiss",
			"fps": 1,
			"name": "missup",
			"indices": []
		},
		{
			"loop": false,
			"offsets": [
				0,
				0
			],
			"anim": "singRIGHTmiss",
			"fps": 1,
			"name": "missright",
			"indices": []
		},
		{
			"offsets": [
				0,
				0
			],
			"loop": false,
			"fps": 2,
			"anim": "firstDeath",
			"indices": [],
			"name": "missup"
		},
		{
			"offsets": [
				0,
				0
			],
			"loop": false,
			"fps": 2,
			"anim": "deathLoop",
			"indices": [],
			"name": "missdown"
		},
		{
			"offsets": [
				0,
				0
			],
			"loop": false,
			"fps": 2,
			"anim": "deathConfirm",
			"indices": [],
			"name": "idle"
		}
	],
	"no_antialiasing": false,
	"image": "characters/FeriHot",
	"position": [
		0,
		0
	],
	"healthicon": "ferihot",
	"flip_x": true,
	"healthbar_colors": [
		255,
		0,
		250
	],
	"camera_position": [
		10,
		0
	],
	"sing_duration": 6.1,
	"scale": 1,
	"arrowsName":"arrowskins/FeriPlantArrows"
}